tests/__init__.py
tests/test_client.py
tests/test_media.py
tests/test_webhooks.py
wistia/__init__.py
wistia/__version__.py
wistia/cli.py
wistia/client.py
wistia/dummy.py
wistia/helpers.py
wistia/schema.py
wistia/webhooks.py
wistiapy-0.0.13.dist-info/LICENSE
wistiapy-0.0.13.dist-info/METADATA
wistiapy-0.0.13.dist-info/WHEEL
wistiapy-0.0.13.dist-info/entry_points.txt
wistiapy-0.0.13.dist-info/top_level.txt
wistiapy-0.0.13.dist-info/RECORD
