Metadata-Version: 2.1
Name: wistiapy
Version: 0.0.13
Summary: A Python client for the Wistia data API
Home-page: https://github.com/Edrolo/wistiapy
Author: Matt Fisher
Author-email: matt@edrolo.com
License: MIT
Keywords: wistia api client
Classifier: Development Status :: 3 - Alpha
Classifier: Intended Audience :: Developers
Classifier: License :: OSI Approved :: MIT License
Classifier: Natural Language :: English
Classifier: Operating System :: OS Independent
Classifier: Programming Language :: Python :: 3
Classifier: Programming Language :: Python :: 3.7
Classifier: Programming Language :: Python :: 3.8
Classifier: Programming Language :: Python :: 3.9
Classifier: Programming Language :: Python :: 3.10
Classifier: Programming Language :: Python :: 3.11
License-File: LICENSE
Requires-Dist: requests (<3.0.0,>=2.22.0)
Requires-Dist: factory-boy (<3.0.0,>=2.7.0)
Requires-Dist: schematics (<3.0.0,>=2.1.1)
Requires-Dist: pydantic (<2.0.0,>=1.8.2)
Provides-Extra: dev
Requires-Dist: black ; extra == 'dev'
Requires-Dist: pytest ; extra == 'dev'
Requires-Dist: responses ; extra == 'dev'
